Metadata-Version: 1.1
Name: calbum
Version: 0.1.12
Summary: An unattended calendar-based photo organiser
Home-page: UNKNOWN
Author: Jonathan Provost
Author-email: jprovost.sh@gmail.com
License: UNKNOWN
Platform: UNKNOWN
Classifier: Development Status :: 5 - Production/Stable
Classifier: Intended Audience :: Developers
Classifier: Intended Audience :: End Users/Desktop
Classifier: License :: OSI Approved :: Apache Software License
Classifier: Operating System :: POSIX
Classifier: Programming Language :: Python :: 2.7
